; Generated by scrip-cc -jvm
; Assemble: java -jar jasmin.jar <file>.j -d .
; Run:      java <classname>

.class public expr_eval
.super java/lang/Object

; Runtime fields
.field static sno_stdout Ljava/io/PrintStream;
.field static sno_input_br Ljava/io/BufferedReader;
.field static sno_kw_TRIM I
.field static sno_kw_ANCHOR I
.field static sno_kw_STNO I
.field static sno_kw_STLIMIT I
.field static sno_kw_STCOUNT I
.field static sno_vars Ljava/util/HashMap;
.field static sno_arrays Ljava/util/HashMap;
.field static sno_data_types Ljava/util/HashMap;
.field static sno_mon_fd Ljava/io/OutputStream;
.field static sno_mon_go_fd Ljava/io/InputStream;
.field static sno_var_stk Ljava/lang/String;
.field static sno_var_Push Ljava/lang/String;
.field static sno_var_x Ljava/lang/String;
.field static sno_var_Pop Ljava/lang/String;
.field static sno_var_arg Ljava/lang/String;
.field static sno_var_op Ljava/lang/String;
.field static sno_var_Unary Ljava/lang/String;
.field static sno_var_dummy Ljava/lang/String;
.field static sno_var_right Ljava/lang/String;
.field static sno_var_left Ljava/lang/String;
.field static sno_var_Binary Ljava/lang/String;
.field static sno_var_integer Ljava/lang/String;
.field static sno_var_exponent Ljava/lang/String;
.field static sno_var_epsilon Ljava/lang/String;
.field static sno_var_real Ljava/lang/String;
.field static sno_var_addop Ljava/lang/String;
.field static sno_var_mulop Ljava/lang/String;
.field static sno_var_constant Ljava/lang/String;
.field static sno_var_primary Ljava/lang/String;
.field static sno_var_expr Ljava/lang/String;
.field static sno_var_factor Ljava/lang/String;
.field static sno_var_term Ljava/lang/String;
.field static sno_var_line Ljava/lang/String;

.method static <clinit>()V
    .limit stack 73
    .limit locals 0
    getstatic       java/lang/System/out Ljava/io/PrintStream;
    putstatic       expr_eval/sno_stdout Ljava/io/PrintStream;
    iconst_0
    putstatic       expr_eval/sno_kw_TRIM I
    iconst_0
    putstatic       expr_eval/sno_kw_ANCHOR I
    iconst_0
    putstatic       expr_eval/sno_kw_STNO I
    iconst_m1
    putstatic       expr_eval/sno_kw_STLIMIT I
    iconst_0
    putstatic       expr_eval/sno_kw_STCOUNT I
    new java/util/HashMap
    dup
    invokespecial java/util/HashMap/<init>()V
    putstatic       expr_eval/sno_vars Ljava/util/HashMap;
    new java/util/HashMap
    dup
    invokespecial java/util/HashMap/<init>()V
    putstatic       expr_eval/sno_arrays Ljava/util/HashMap;
    new java/util/HashMap
    dup
    invokespecial java/util/HashMap/<init>()V
    putstatic       expr_eval/sno_data_types Ljava/util/HashMap;
    ldc             ""
    putstatic       expr_eval/sno_var_stk Ljava/lang/String;
    getstatic       expr_eval/sno_vars Ljava/util/HashMap;
    ldc             "stk"
    ldc             ""
    invokevirtual   java/util/HashMap/put(Ljava/lang/Object;Ljava/lang/Object;)Ljava/lang/Object;
    pop
    ldc             ""
    putstatic       expr_eval/sno_var_Push Ljava/lang/String;
    getstatic       expr_eval/sno_vars Ljava/util/HashMap;
    ldc             "Push"
    ldc             ""
    invokevirtual   java/util/HashMap/put(Ljava/lang/Object;Ljava/lang/Object;)Ljava/lang/Object;
    pop
    ldc             ""
    putstatic       expr_eval/sno_var_x Ljava/lang/String;
    getstatic       expr_eval/sno_vars Ljava/util/HashMap;
    ldc             "x"
    ldc             ""
    invokevirtual   java/util/HashMap/put(Ljava/lang/Object;Ljava/lang/Object;)Ljava/lang/Object;
    pop
    ldc             ""
    putstatic       expr_eval/sno_var_Pop Ljava/lang/String;
    getstatic       expr_eval/sno_vars Ljava/util/HashMap;
    ldc             "Pop"
    ldc             ""
    invokevirtual   java/util/HashMap/put(Ljava/lang/Object;Ljava/lang/Object;)Ljava/lang/Object;
    pop
    ldc             ""
    putstatic       expr_eval/sno_var_arg Ljava/lang/String;
    getstatic       expr_eval/sno_vars Ljava/util/HashMap;
    ldc             "arg"
    ldc             ""
    invokevirtual   java/util/HashMap/put(Ljava/lang/Object;Ljava/lang/Object;)Ljava/lang/Object;
    pop
    ldc             ""
    putstatic       expr_eval/sno_var_op Ljava/lang/String;
    getstatic       expr_eval/sno_vars Ljava/util/HashMap;
    ldc             "op"
    ldc             ""
    invokevirtual   java/util/HashMap/put(Ljava/lang/Object;Ljava/lang/Object;)Ljava/lang/Object;
    pop
    ldc             ""
    putstatic       expr_eval/sno_var_Unary Ljava/lang/String;
    getstatic       expr_eval/sno_vars Ljava/util/HashMap;
    ldc             "Unary"
    ldc             ""
    invokevirtual   java/util/HashMap/put(Ljava/lang/Object;Ljava/lang/Object;)Ljava/lang/Object;
    pop
    ldc             ""
    putstatic       expr_eval/sno_var_dummy Ljava/lang/String;
    getstatic       expr_eval/sno_vars Ljava/util/HashMap;
    ldc             "dummy"
    ldc             ""
    invokevirtual   java/util/HashMap/put(Ljava/lang/Object;Ljava/lang/Object;)Ljava/lang/Object;
    pop
    ldc             ""
    putstatic       expr_eval/sno_var_right Ljava/lang/String;
    getstatic       expr_eval/sno_vars Ljava/util/HashMap;
    ldc             "right"
    ldc             ""
    invokevirtual   java/util/HashMap/put(Ljava/lang/Object;Ljava/lang/Object;)Ljava/lang/Object;
    pop
    ldc             ""
    putstatic       expr_eval/sno_var_left Ljava/lang/String;
    getstatic       expr_eval/sno_vars Ljava/util/HashMap;
    ldc             "left"
    ldc             ""
    invokevirtual   java/util/HashMap/put(Ljava/lang/Object;Ljava/lang/Object;)Ljava/lang/Object;
    pop
    ldc             ""
    putstatic       expr_eval/sno_var_Binary Ljava/lang/String;
    getstatic       expr_eval/sno_vars Ljava/util/HashMap;
    ldc             "Binary"
    ldc             ""
    invokevirtual   java/util/HashMap/put(Ljava/lang/Object;Ljava/lang/Object;)Ljava/lang/Object;
    pop
    ldc             ""
    putstatic       expr_eval/sno_var_integer Ljava/lang/String;
    getstatic       expr_eval/sno_vars Ljava/util/HashMap;
    ldc             "integer"
    ldc             ""
    invokevirtual   java/util/HashMap/put(Ljava/lang/Object;Ljava/lang/Object;)Ljava/lang/Object;
    pop
    ldc             ""
    putstatic       expr_eval/sno_var_exponent Ljava/lang/String;
    getstatic       expr_eval/sno_vars Ljava/util/HashMap;
    ldc             "exponent"
    ldc             ""
    invokevirtual   java/util/HashMap/put(Ljava/lang/Object;Ljava/lang/Object;)Ljava/lang/Object;
    pop
    ldc             ""
    putstatic       expr_eval/sno_var_epsilon Ljava/lang/String;
    getstatic       expr_eval/sno_vars Ljava/util/HashMap;
    ldc             "epsilon"
    ldc             ""
    invokevirtual   java/util/HashMap/put(Ljava/lang/Object;Ljava/lang/Object;)Ljava/lang/Object;
    pop
    ldc             ""
    putstatic       expr_eval/sno_var_real Ljava/lang/String;
    getstatic       expr_eval/sno_vars Ljava/util/HashMap;
    ldc             "real"
    ldc             ""
    invokevirtual   java/util/HashMap/put(Ljava/lang/Object;Ljava/lang/Object;)Ljava/lang/Object;
    pop
    ldc             ""
    putstatic       expr_eval/sno_var_addop Ljava/lang/String;
    getstatic       expr_eval/sno_vars Ljava/util/HashMap;
    ldc             "addop"
    ldc             ""
    invokevirtual   java/util/HashMap/put(Ljava/lang/Object;Ljava/lang/Object;)Ljava/lang/Object;
    pop
    ldc             ""
    putstatic       expr_eval/sno_var_mulop Ljava/lang/String;
    getstatic       expr_eval/sno_vars Ljava/util/HashMap;
    ldc             "mulop"
    ldc             ""
    invokevirtual   java/util/HashMap/put(Ljava/lang/Object;Ljava/lang/Object;)Ljava/lang/Object;
    pop
    ldc             ""
    putstatic       expr_eval/sno_var_constant Ljava/lang/String;
    getstatic       expr_eval/sno_vars Ljava/util/HashMap;
    ldc             "constant"
    ldc             ""
    invokevirtual   java/util/HashMap/put(Ljava/lang/Object;Ljava/lang/Object;)Ljava/lang/Object;
    pop
    ldc             ""
    putstatic       expr_eval/sno_var_primary Ljava/lang/String;
    getstatic       expr_eval/sno_vars Ljava/util/HashMap;
    ldc             "primary"
    ldc             ""
    invokevirtual   java/util/HashMap/put(Ljava/lang/Object;Ljava/lang/Object;)Ljava/lang/Object;
    pop
    ldc             ""
    putstatic       expr_eval/sno_var_expr Ljava/lang/String;
    getstatic       expr_eval/sno_vars Ljava/util/HashMap;
    ldc             "expr"
    ldc             ""
    invokevirtual   java/util/HashMap/put(Ljava/lang/Object;Ljava/lang/Object;)Ljava/lang/Object;
    pop
    ldc             ""
    putstatic       expr_eval/sno_var_factor Ljava/lang/String;
    getstatic       expr_eval/sno_vars Ljava/util/HashMap;
    ldc             "factor"
    ldc             ""
    invokevirtual   java/util/HashMap/put(Ljava/lang/Object;Ljava/lang/Object;)Ljava/lang/Object;
    pop
    ldc             ""
    putstatic       expr_eval/sno_var_term Ljava/lang/String;
    getstatic       expr_eval/sno_vars Ljava/util/HashMap;
    ldc             "term"
    ldc             ""
    invokevirtual   java/util/HashMap/put(Ljava/lang/Object;Ljava/lang/Object;)Ljava/lang/Object;
    pop
    ldc             ""
    putstatic       expr_eval/sno_var_line Ljava/lang/String;
    getstatic       expr_eval/sno_vars Ljava/util/HashMap;
    ldc             "line"
    ldc             ""
    invokevirtual   java/util/HashMap/put(Ljava/lang/Object;Ljava/lang/Object;)Ljava/lang/Object;
    pop
    return
.end method

.method static sno_mon_init()V
    .limit stack 6
    .limit locals 2
    ldc "MONITOR_READY_PIPE"
    invokestatic java/lang/System/getenv(Ljava/lang/String;)Ljava/lang/String;
    astore_0
    aload_0
    ifnull Lsmi_done
    aload_0
    invokevirtual java/lang/String/isEmpty()Z
    ifne Lsmi_done
    new java/io/FileOutputStream
    dup
    aload_0
    iconst_1
    invokespecial java/io/FileOutputStream/<init>(Ljava/lang/String;Z)V
    putstatic expr_eval/sno_mon_fd Ljava/io/OutputStream;
    ldc "MONITOR_GO_PIPE"
    invokestatic java/lang/System/getenv(Ljava/lang/String;)Ljava/lang/String;
    astore_1
    aload_1
    ifnull Lsmi_done
    aload_1
    invokevirtual java/lang/String/isEmpty()Z
    ifne Lsmi_done
    new java/io/FileInputStream
    dup
    aload_1
    invokespecial java/io/FileInputStream/<init>(Ljava/lang/String;)V
    putstatic expr_eval/sno_mon_go_fd Ljava/io/InputStream;
Lsmi_done:
    return
.end method

.method public static main([Ljava/lang/String;)V
    .limit stack 16
    .limit locals 32

    invokestatic expr_eval/sno_mon_init()V
    getstatic expr_eval/sno_kw_STNO I
    iconst_1
    iadd
    putstatic expr_eval/sno_kw_STNO I
    invokestatic expr_eval/sno_stcount_tick()V
    ldc ""
    pop
    getstatic expr_eval/sno_kw_STNO I
    iconst_1
    iadd
    putstatic expr_eval/sno_kw_STNO I
    invokestatic expr_eval/sno_stcount_tick()V
    invokestatic expr_eval/sno_table_new()Ljava/lang/String;
    dup
    ifnonnull Lvar_ok_0
    pop
    goto Lvar_fail_0
Lvar_ok_0:
    ldc "stk"
    swap
    invokestatic expr_eval/sno_var_put(Ljava/lang/String;Ljava/lang/String;)V
    goto L_PushEnd
Lvar_fail_0:
; === PushEnd =========================================================
L_PushEnd:
    getstatic expr_eval/sno_kw_STNO I
    iconst_1
    iadd
    putstatic expr_eval/sno_kw_STNO I
    invokestatic expr_eval/sno_stcount_tick()V
    ldc ""
    pop
    goto L_PopEnd
; === PopEnd ==========================================================
L_PopEnd:
    getstatic expr_eval/sno_kw_STNO I
    iconst_1
    iadd
    putstatic expr_eval/sno_kw_STNO I
    invokestatic expr_eval/sno_stcount_tick()V
    ldc ""
    pop
    goto L_UnaryEnd
; === UnaryEnd ========================================================
L_UnaryEnd:
    getstatic expr_eval/sno_kw_STNO I
    iconst_1
    iadd
    putstatic expr_eval/sno_kw_STNO I
    invokestatic expr_eval/sno_stcount_tick()V
    ldc ""
    pop
    goto L_BinaryEnd
; === BinaryEnd =======================================================
L_BinaryEnd:
    getstatic expr_eval/sno_kw_STNO I
    iconst_1
    iadd
    putstatic expr_eval/sno_kw_STNO I
    invokestatic expr_eval/sno_stcount_tick()V
    ldc ""
    dup
    ifnonnull Lvar_ok_1
    pop
    goto Lvar_fail_1
Lvar_ok_1:
    ldc "integer"
    swap
    invokestatic expr_eval/sno_var_put(Ljava/lang/String;Ljava/lang/String;)V
Lvar_fail_1:
    getstatic expr_eval/sno_kw_STNO I
    iconst_1
    iadd
    putstatic expr_eval/sno_kw_STNO I
    invokestatic expr_eval/sno_stcount_tick()V
    new java/lang/StringBuilder
    dup
    invokespecial java/lang/StringBuilder/<init>()V
    ldc ""
    dup
    ifnonnull Lconc_ok_0_0
    pop
    pop
    aconst_null
    goto Lconc_done_0
Lconc_ok_0_0:
    invokevirtual java/lang/StringBuilder/append(Ljava/lang/String;)Ljava/lang/StringBuilder;
    ldc ""
    dup
    ifnonnull Lconc_ok_0_1
    pop
    pop
    aconst_null
    goto Lconc_done_0
Lconc_ok_0_1:
    invokevirtual java/lang/StringBuilder/append(Ljava/lang/String;)Ljava/lang/StringBuilder;
    ldc "integer"
    invokestatic expr_eval/sno_indr_get(Ljava/lang/String;)Ljava/lang/String;
    dup
    ifnonnull Lconc_ok_0_2
    pop
    pop
    aconst_null
    goto Lconc_done_0
Lconc_ok_0_2:
    invokevirtual java/lang/StringBuilder/append(Ljava/lang/String;)Ljava/lang/StringBuilder;
    invokevirtual java/lang/StringBuilder/toString()Ljava/lang/String;
Lconc_done_0:
    dup
    ifnonnull Lvar_ok_2
    pop
    goto Lvar_fail_2
Lvar_ok_2:
    ldc "exponent"
    swap
    invokestatic expr_eval/sno_var_put(Ljava/lang/String;Ljava/lang/String;)V
Lvar_fail_2:
    getstatic expr_eval/sno_kw_STNO I
    iconst_1
    iadd
    putstatic expr_eval/sno_kw_STNO I
    invokestatic expr_eval/sno_stcount_tick()V
    ldc ""
    dup
    ifnonnull Lvar_ok_3
    pop
    goto Lvar_fail_3
Lvar_ok_3:
    ldc "real"
    swap
    invokestatic expr_eval/sno_var_put(Ljava/lang/String;Ljava/lang/String;)V
Lvar_fail_3:
    getstatic expr_eval/sno_kw_STNO I
    iconst_1
    iadd
    putstatic expr_eval/sno_kw_STNO I
    invokestatic expr_eval/sno_stcount_tick()V
    ldc ""
    dup
    ifnonnull Lvar_ok_4
    pop
    goto Lvar_fail_4
Lvar_ok_4:
    ldc "addop"
    swap
    invokestatic expr_eval/sno_var_put(Ljava/lang/String;Ljava/lang/String;)V
Lvar_fail_4:
    getstatic expr_eval/sno_kw_STNO I
    iconst_1
    iadd
    putstatic expr_eval/sno_kw_STNO I
    invokestatic expr_eval/sno_stcount_tick()V
    ldc ""
    dup
    ifnonnull Lvar_ok_5
    pop
    goto Lvar_fail_5
Lvar_ok_5:
    ldc "mulop"
    swap
    invokestatic expr_eval/sno_var_put(Ljava/lang/String;Ljava/lang/String;)V
Lvar_fail_5:
    getstatic expr_eval/sno_kw_STNO I
    iconst_1
    iadd
    putstatic expr_eval/sno_kw_STNO I
    invokestatic expr_eval/sno_stcount_tick()V
    ldc ""
    dup
    ifnonnull Lvar_ok_6
    pop
    goto Lvar_fail_6
Lvar_ok_6:
    ldc "constant"
    swap
    invokestatic expr_eval/sno_var_put(Ljava/lang/String;Ljava/lang/String;)V
Lvar_fail_6:
    getstatic expr_eval/sno_kw_STNO I
    iconst_1
    iadd
    putstatic expr_eval/sno_kw_STNO I
    invokestatic expr_eval/sno_stcount_tick()V
    ldc ""
    dup
    ifnonnull Lvar_ok_7
    pop
    goto Lvar_fail_7
Lvar_ok_7:
    ldc "primary"
    swap
    invokestatic expr_eval/sno_var_put(Ljava/lang/String;Ljava/lang/String;)V
Lvar_fail_7:
    getstatic expr_eval/sno_kw_STNO I
    iconst_1
    iadd
    putstatic expr_eval/sno_kw_STNO I
    invokestatic expr_eval/sno_stcount_tick()V
    ldc ""
    dup
    ifnonnull Lvar_ok_8
    pop
    goto Lvar_fail_8
Lvar_ok_8:
    ldc "factor"
    swap
    invokestatic expr_eval/sno_var_put(Ljava/lang/String;Ljava/lang/String;)V
Lvar_fail_8:
    getstatic expr_eval/sno_kw_STNO I
    iconst_1
    iadd
    putstatic expr_eval/sno_kw_STNO I
    invokestatic expr_eval/sno_stcount_tick()V
    ldc ""
    dup
    ifnonnull Lvar_ok_9
    pop
    goto Lvar_fail_9
Lvar_ok_9:
    ldc "term"
    swap
    invokestatic expr_eval/sno_var_put(Ljava/lang/String;Ljava/lang/String;)V
Lvar_fail_9:
    getstatic expr_eval/sno_kw_STNO I
    iconst_1
    iadd
    putstatic expr_eval/sno_kw_STNO I
    invokestatic expr_eval/sno_stcount_tick()V
    ldc ""
    dup
    ifnonnull Lvar_ok_10
    pop
    goto Lvar_fail_10
Lvar_ok_10:
    ldc "expr"
    swap
    invokestatic expr_eval/sno_var_put(Ljava/lang/String;Ljava/lang/String;)V
Lvar_fail_10:
    getstatic expr_eval/sno_kw_STNO I
    iconst_1
    iadd
    putstatic expr_eval/sno_kw_STNO I
    invokestatic expr_eval/sno_stcount_tick()V
    ldc "TRIM"
    ldc "1"
    invokestatic expr_eval/sno_kw_set(Ljava/lang/String;Ljava/lang/String;)V
; === loop ============================================================
L_loop:
    getstatic expr_eval/sno_kw_STNO I
    iconst_1
    iadd
    putstatic expr_eval/sno_kw_STNO I
    invokestatic expr_eval/sno_stcount_tick()V
    invokestatic expr_eval/sno_input_read()Ljava/lang/String;
    dup
    ifnonnull Linp_ok_0
    pop
    goto L_END
Linp_ok_0:
    ldc "line"
    swap
    invokestatic expr_eval/sno_var_put(Ljava/lang/String;Ljava/lang/String;)V
    getstatic expr_eval/sno_kw_STNO I
    iconst_1
    iadd
    putstatic expr_eval/sno_kw_STNO I
    invokestatic expr_eval/sno_stcount_tick()V
; --- pattern match statement ---
    ldc "line"
    invokestatic expr_eval/sno_indr_get(Ljava/lang/String;)Ljava/lang/String;
    astore 6
    iconst_0
    istore 7
    aload 6
    invokevirtual java/lang/String/length()I
    istore 8
Jpat0_retry:
    iload 7
    istore 9
    ldc "0"
    invokestatic java/lang/Integer/parseInt(Ljava/lang/String;)I
    istore 10
    iload 7
    iload 10
    if_icmpne Jpat0_tfail
    goto Jn1_seq_mid
Jn1_seq_mid:
    ; E_VART expr → named pattern inline expansion
    iload 7
    istore 11
    ; STUB: unhandled pattern node kind 8
    goto Jn7_seq_mid
Jn7_seq_mid:
    ; E_VART addop → named pattern inline expansion
    iload 7
    istore 12
    iload 7
    iload 8
    if_icmpge Jn5_alt_right
    aload 6
    iload 7
    invokevirtual java/lang/String/charAt(I)C
    invokestatic java/lang/String/valueOf(C)Ljava/lang/String;
    astore 13
    ldc "+-"
    aload 13
    invokevirtual java/lang/String/contains(Ljava/lang/CharSequence;)Z
    ifeq Jn5_alt_right
    iinc 7 1
    goto Jn11_nam_ok
Jn11_nam_ok:
    ldc ""
    aload 6
    iload 12
    iload 7
    invokevirtual java/lang/String/substring(II)Ljava/lang/String;
    invokestatic expr_eval/sno_var_put(Ljava/lang/String;Ljava/lang/String;)V
    goto Jn9_seq_mid
Jn9_seq_mid:
    iload 7
    istore 14
    ; STUB: unhandled pattern node kind 8
    goto Jn13_nam_ok
Jn13_nam_ok:
    ldc ""
    aload 6
    iload 14
    iload 7
    invokevirtual java/lang/String/substring(II)Ljava/lang/String;
    invokestatic expr_eval/sno_var_put(Ljava/lang/String;Ljava/lang/String;)V
    goto Jn3_seq_mid
Jn5_alt_right:
    iload 11
    istore 7
    ; STUB: unhandled pattern node kind 8
    goto Jn3_seq_mid
Jn3_seq_mid:
    ldc "0"
    invokestatic java/lang/Integer/parseInt(Ljava/lang/String;)I
    istore 15
    iload 8
    iload 15
    isub
    iload 7
    if_icmpne Jpat0_tfail
    goto Jpat0_tok
Jpat0_tok:
    goto Jpat0_success
Jpat0_tfail:
    getstatic expr_eval/sno_kw_ANCHOR I
    ifeq Jpat0_askip
    goto Jpat0_fail
Jpat0_askip:
    iinc 7 1
    iload 7
    iload 8
    if_icmple Jpat0_retry
    goto Jpat0_fail
Jpat0_success:
    goto Jpat0_after
Jpat0_fail:
    goto L_error
Jpat0_after:
    getstatic expr_eval/sno_kw_STNO I
    iconst_1
    iadd
    putstatic expr_eval/sno_kw_STNO I
    invokestatic expr_eval/sno_stcount_tick()V
    invokestatic expr_eval/sno_userfn_Pop()Ljava/lang/String;
    dup
    ifnonnull Lout_ok_0
    pop
    goto Lout_fail_0
Lout_ok_0:
    getstatic expr_eval/sno_stdout Ljava/io/PrintStream;
    swap
    invokevirtual java/io/PrintStream/println(Ljava/lang/String;)V
    goto L_loop
Lout_fail_0:
    goto L_loop
; === error ===========================================================
L_error:
    getstatic expr_eval/sno_kw_STNO I
    iconst_1
    iadd
    putstatic expr_eval/sno_kw_STNO I
    invokestatic expr_eval/sno_stcount_tick()V
    ldc "Bad input, try again"
    dup
    ifnonnull Lout_ok_1
    pop
    goto Lout_fail_1
Lout_ok_1:
    getstatic expr_eval/sno_stdout Ljava/io/PrintStream;
    swap
    invokevirtual java/io/PrintStream/println(Ljava/lang/String;)V
    goto L_loop
Lout_fail_1:
    goto L_loop
; === END =============================================================
L_END:
    nop
; program end
    return
.end method
.method static sno_userfn_Push(Ljava/lang/String;)Ljava/lang/String;
    .limit stack 16
    .limit locals 64

    ldc "x"
    invokestatic expr_eval/sno_indr_get(Ljava/lang/String;)Ljava/lang/String;
    astore 1
    ldc "Push"
    invokestatic expr_eval/sno_indr_get(Ljava/lang/String;)Ljava/lang/String;
    astore 2
    ldc "x"
    aload 0
    invokestatic expr_eval/sno_var_put(Ljava/lang/String;Ljava/lang/String;)V
    ldc "Push"
    ldc ""
    invokestatic expr_eval/sno_var_put(Ljava/lang/String;Ljava/lang/String;)V
; === Push ============================================================
Lf0_Push:
    getstatic expr_eval/sno_kw_STNO I
    iconst_1
    iadd
    putstatic expr_eval/sno_kw_STNO I
    invokestatic expr_eval/sno_stcount_tick()V
    ldc "stk"
    invokestatic expr_eval/sno_indr_get(Ljava/lang/String;)Ljava/lang/String;
    ldc "0"
    ldc "stk"
    invokestatic expr_eval/sno_indr_get(Ljava/lang/String;)Ljava/lang/String;
    ldc "0"
    invokestatic expr_eval/sno_array_get(Ljava/lang/String;Ljava/lang/String;)Ljava/lang/String;
    invokestatic expr_eval/sno_to_double(Ljava/lang/String;)D
    ldc "1"
    invokestatic expr_eval/sno_to_double(Ljava/lang/String;)D
    dadd
    dstore 4
    dload 4
    d2l
    lstore 6
    lload 6
    l2d
    dload 4
    dcmpl
    ifne Larf_0
    lload 6
    invokestatic java/lang/Long/toString(J)Ljava/lang/String;
    goto Lard_0
Larf_0:
    dload 4
    invokestatic java/lang/Double/toString(D)Ljava/lang/String;
Lard_0:
    invokestatic expr_eval/sno_array_put(Ljava/lang/String;Ljava/lang/String;Ljava/lang/String;)V
; unhandled stmt form
    nop
    getstatic expr_eval/sno_kw_STNO I
    iconst_1
    iadd
    putstatic expr_eval/sno_kw_STNO I
    invokestatic expr_eval/sno_stcount_tick()V
    ldc ""
    dup
    ifnonnull Lvar_ok_11
    pop
    goto Lvar_fail_11
Lvar_ok_11:
    ldc "Push"
    swap
    invokestatic expr_eval/sno_var_put(Ljava/lang/String;Ljava/lang/String;)V
Lvar_fail_11:
    getstatic expr_eval/sno_kw_STNO I
    iconst_1
    iadd
    putstatic expr_eval/sno_kw_STNO I
    invokestatic expr_eval/sno_stcount_tick()V
    ldc "Push"
    invokestatic expr_eval/sno_indr_get(Ljava/lang/String;)Ljava/lang/String;
    ldc "x"
    invokestatic expr_eval/sno_indr_get(Ljava/lang/String;)Ljava/lang/String;
    invokestatic expr_eval/sno_indr_set(Ljava/lang/String;Ljava/lang/String;)V
    goto Jfn0_return
Jfn0_return:
    ldc "x"
    aload 1
    invokestatic expr_eval/sno_var_put(Ljava/lang/String;Ljava/lang/String;)V
    ldc "Push"
    invokestatic expr_eval/sno_indr_get(Ljava/lang/String;)Ljava/lang/String;
    ldc "Push"
    aload 2
    invokestatic expr_eval/sno_var_put(Ljava/lang/String;Ljava/lang/String;)V
    areturn
Jfn0_freturn:
    ldc "x"
    aload 1
    invokestatic expr_eval/sno_var_put(Ljava/lang/String;Ljava/lang/String;)V
    ldc "Push"
    aload 2
    invokestatic expr_eval/sno_var_put(Ljava/lang/String;Ljava/lang/String;)V
    aconst_null
    areturn
.end method

.method static sno_userfn_Pop()Ljava/lang/String;
    .limit stack 16
    .limit locals 64

    ldc "Pop"
    invokestatic expr_eval/sno_indr_get(Ljava/lang/String;)Ljava/lang/String;
    astore 0
    ldc "Pop"
    ldc ""
    invokestatic expr_eval/sno_var_put(Ljava/lang/String;Ljava/lang/String;)V
; === Pop =============================================================
Lf1_Pop:
    getstatic expr_eval/sno_kw_STNO I
    iconst_1
    iadd
    putstatic expr_eval/sno_kw_STNO I
    invokestatic expr_eval/sno_stcount_tick()V
    ldc "stk"
    invokestatic expr_eval/sno_indr_get(Ljava/lang/String;)Ljava/lang/String;
    ldc "stk"
    invokestatic expr_eval/sno_indr_get(Ljava/lang/String;)Ljava/lang/String;
    ldc "0"
    invokestatic expr_eval/sno_array_get(Ljava/lang/String;Ljava/lang/String;)Ljava/lang/String;
    invokestatic expr_eval/sno_array_get(Ljava/lang/String;Ljava/lang/String;)Ljava/lang/String;
    dup
    ifnonnull Lvar_ok_12
    pop
    goto Lvar_fail_12
Lvar_ok_12:
    ldc "Pop"
    swap
    invokestatic expr_eval/sno_var_put(Ljava/lang/String;Ljava/lang/String;)V
Lvar_fail_12:
    getstatic expr_eval/sno_kw_STNO I
    iconst_1
    iadd
    putstatic expr_eval/sno_kw_STNO I
    invokestatic expr_eval/sno_stcount_tick()V
    ldc "stk"
    invokestatic expr_eval/sno_indr_get(Ljava/lang/String;)Ljava/lang/String;
    ldc "0"
    ldc "stk"
    invokestatic expr_eval/sno_indr_get(Ljava/lang/String;)Ljava/lang/String;
    ldc "0"
    invokestatic expr_eval/sno_array_get(Ljava/lang/String;Ljava/lang/String;)Ljava/lang/String;
    invokestatic expr_eval/sno_to_double(Ljava/lang/String;)D
    ldc "1"
    invokestatic expr_eval/sno_to_double(Ljava/lang/String;)D
    dsub
    dstore 2
    dload 2
    d2l
    lstore 4
    lload 4
    l2d
    dload 2
    dcmpl
    ifne Larf_1
    lload 4
    invokestatic java/lang/Long/toString(J)Ljava/lang/String;
    goto Lard_1
Larf_1:
    dload 2
    invokestatic java/lang/Double/toString(D)Ljava/lang/String;
Lard_1:
    invokestatic expr_eval/sno_array_put(Ljava/lang/String;Ljava/lang/String;Ljava/lang/String;)V
    goto Jfn1_return
; unhandled stmt form
    nop
Jfn1_return:
    ldc "Pop"
    invokestatic expr_eval/sno_indr_get(Ljava/lang/String;)Ljava/lang/String;
    ldc "Pop"
    aload 0
    invokestatic expr_eval/sno_var_put(Ljava/lang/String;Ljava/lang/String;)V
    areturn
Jfn1_freturn:
    ldc "Pop"
    aload 0
    invokestatic expr_eval/sno_var_put(Ljava/lang/String;Ljava/lang/String;)V
    aconst_null
    areturn
.end method

.method static sno_userfn_Unary()Ljava/lang/String;
    .limit stack 16
    .limit locals 64

    ldc "arg"
    invokestatic expr_eval/sno_indr_get(Ljava/lang/String;)Ljava/lang/String;
    astore 0
    ldc "op"
    invokestatic expr_eval/sno_indr_get(Ljava/lang/String;)Ljava/lang/String;
    astore 1
    ldc "Unary"
    invokestatic expr_eval/sno_indr_get(Ljava/lang/String;)Ljava/lang/String;
    astore 2
    ldc "arg"
    ldc ""
    invokestatic expr_eval/sno_var_put(Ljava/lang/String;Ljava/lang/String;)V
    ldc "op"
    ldc ""
    invokestatic expr_eval/sno_var_put(Ljava/lang/String;Ljava/lang/String;)V
    ldc "Unary"
    ldc ""
    invokestatic expr_eval/sno_var_put(Ljava/lang/String;Ljava/lang/String;)V
; === Unary ===========================================================
Lf2_Unary:
    getstatic expr_eval/sno_kw_STNO I
    iconst_1
    iadd
    putstatic expr_eval/sno_kw_STNO I
    invokestatic expr_eval/sno_stcount_tick()V
    invokestatic expr_eval/sno_userfn_Pop()Ljava/lang/String;
    dup
    ifnonnull Lvar_ok_13
    pop
    goto Lvar_fail_13
Lvar_ok_13:
    ldc "arg"
    swap
    invokestatic expr_eval/sno_var_put(Ljava/lang/String;Ljava/lang/String;)V
Lvar_fail_13:
    getstatic expr_eval/sno_kw_STNO I
    iconst_1
    iadd
    putstatic expr_eval/sno_kw_STNO I
    invokestatic expr_eval/sno_stcount_tick()V
    invokestatic expr_eval/sno_userfn_Pop()Ljava/lang/String;
    dup
    ifnonnull Lvar_ok_14
    pop
    goto Lvar_fail_14
Lvar_ok_14:
    ldc "op"
    swap
    invokestatic expr_eval/sno_var_put(Ljava/lang/String;Ljava/lang/String;)V
Lvar_fail_14:
    getstatic expr_eval/sno_kw_STNO I
    iconst_1
    iadd
    putstatic expr_eval/sno_kw_STNO I
    invokestatic expr_eval/sno_stcount_tick()V
; unhandled stmt form
    nop
    getstatic expr_eval/sno_kw_STNO I
    iconst_1
    iadd
    putstatic expr_eval/sno_kw_STNO I
    invokestatic expr_eval/sno_stcount_tick()V
    ldc ""
    dup
    ifnonnull Lvar_ok_15
    pop
    goto Lvar_fail_15
Lvar_ok_15:
    ldc "Unary"
    swap
    invokestatic expr_eval/sno_var_put(Ljava/lang/String;Ljava/lang/String;)V
    goto Jfn2_return
Lvar_fail_15:
Jfn2_return:
    ldc "arg"
    aload 0
    invokestatic expr_eval/sno_var_put(Ljava/lang/String;Ljava/lang/String;)V
    ldc "op"
    aload 1
    invokestatic expr_eval/sno_var_put(Ljava/lang/String;Ljava/lang/String;)V
    ldc "Unary"
    invokestatic expr_eval/sno_indr_get(Ljava/lang/String;)Ljava/lang/String;
    ldc "Unary"
    aload 2
    invokestatic expr_eval/sno_var_put(Ljava/lang/String;Ljava/lang/String;)V
    areturn
Jfn2_freturn:
    ldc "arg"
    aload 0
    invokestatic expr_eval/sno_var_put(Ljava/lang/String;Ljava/lang/String;)V
    ldc "op"
    aload 1
    invokestatic expr_eval/sno_var_put(Ljava/lang/String;Ljava/lang/String;)V
    ldc "Unary"
    aload 2
    invokestatic expr_eval/sno_var_put(Ljava/lang/String;Ljava/lang/String;)V
    aconst_null
    areturn
.end method

.method static sno_userfn_Binary()Ljava/lang/String;
    .limit stack 16
    .limit locals 64

    ldc "op"
    invokestatic expr_eval/sno_indr_get(Ljava/lang/String;)Ljava/lang/String;
    astore 0
    ldc "left"
    invokestatic expr_eval/sno_indr_get(Ljava/lang/String;)Ljava/lang/String;
    astore 1
    ldc "right"
    invokestatic expr_eval/sno_indr_get(Ljava/lang/String;)Ljava/lang/String;
    astore 2
    ldc "Binary"
    invokestatic expr_eval/sno_indr_get(Ljava/lang/String;)Ljava/lang/String;
    astore 3
    ldc "op"
    ldc ""
    invokestatic expr_eval/sno_var_put(Ljava/lang/String;Ljava/lang/String;)V
    ldc "left"
    ldc ""
    invokestatic expr_eval/sno_var_put(Ljava/lang/String;Ljava/lang/String;)V
    ldc "right"
    ldc ""
    invokestatic expr_eval/sno_var_put(Ljava/lang/String;Ljava/lang/String;)V
    ldc "Binary"
    ldc ""
    invokestatic expr_eval/sno_var_put(Ljava/lang/String;Ljava/lang/String;)V
; === Binary ==========================================================
Lf3_Binary:
    getstatic expr_eval/sno_kw_STNO I
    iconst_1
    iadd
    putstatic expr_eval/sno_kw_STNO I
    invokestatic expr_eval/sno_stcount_tick()V
    invokestatic expr_eval/sno_userfn_Pop()Ljava/lang/String;
    dup
    ifnonnull Lvar_ok_16
    pop
    goto Lvar_fail_16
Lvar_ok_16:
    ldc "right"
    swap
    invokestatic expr_eval/sno_var_put(Ljava/lang/String;Ljava/lang/String;)V
Lvar_fail_16:
    getstatic expr_eval/sno_kw_STNO I
    iconst_1
    iadd
    putstatic expr_eval/sno_kw_STNO I
    invokestatic expr_eval/sno_stcount_tick()V
    invokestatic expr_eval/sno_userfn_Pop()Ljava/lang/String;
    dup
    ifnonnull Lvar_ok_17
    pop
    goto Lvar_fail_17
Lvar_ok_17:
    ldc "op"
    swap
    invokestatic expr_eval/sno_var_put(Ljava/lang/String;Ljava/lang/String;)V
Lvar_fail_17:
    getstatic expr_eval/sno_kw_STNO I
    iconst_1
    iadd
    putstatic expr_eval/sno_kw_STNO I
    invokestatic expr_eval/sno_stcount_tick()V
    invokestatic expr_eval/sno_userfn_Pop()Ljava/lang/String;
    dup
    ifnonnull Lvar_ok_18
    pop
    goto Lvar_fail_18
Lvar_ok_18:
    ldc "left"
    swap
    invokestatic expr_eval/sno_var_put(Ljava/lang/String;Ljava/lang/String;)V
Lvar_fail_18:
    getstatic expr_eval/sno_kw_STNO I
    iconst_1
    iadd
    putstatic expr_eval/sno_kw_STNO I
    invokestatic expr_eval/sno_stcount_tick()V
; unhandled stmt form
    nop
    getstatic expr_eval/sno_kw_STNO I
    iconst_1
    iadd
    putstatic expr_eval/sno_kw_STNO I
    invokestatic expr_eval/sno_stcount_tick()V
    ldc ""
    dup
    ifnonnull Lvar_ok_19
    pop
    goto Lvar_fail_19
Lvar_ok_19:
    ldc "Binary"
    swap
    invokestatic expr_eval/sno_var_put(Ljava/lang/String;Ljava/lang/String;)V
    goto Jfn3_return
Lvar_fail_19:
Jfn3_return:
    ldc "op"
    aload 0
    invokestatic expr_eval/sno_var_put(Ljava/lang/String;Ljava/lang/String;)V
    ldc "left"
    aload 1
    invokestatic expr_eval/sno_var_put(Ljava/lang/String;Ljava/lang/String;)V
    ldc "right"
    aload 2
    invokestatic expr_eval/sno_var_put(Ljava/lang/String;Ljava/lang/String;)V
    ldc "Binary"
    invokestatic expr_eval/sno_indr_get(Ljava/lang/String;)Ljava/lang/String;
    ldc "Binary"
    aload 3
    invokestatic expr_eval/sno_var_put(Ljava/lang/String;Ljava/lang/String;)V
    areturn
Jfn3_freturn:
    ldc "op"
    aload 0
    invokestatic expr_eval/sno_var_put(Ljava/lang/String;Ljava/lang/String;)V
    ldc "left"
    aload 1
    invokestatic expr_eval/sno_var_put(Ljava/lang/String;Ljava/lang/String;)V
    ldc "right"
    aload 2
    invokestatic expr_eval/sno_var_put(Ljava/lang/String;Ljava/lang/String;)V
    ldc "Binary"
    aload 3
    invokestatic expr_eval/sno_var_put(Ljava/lang/String;Ljava/lang/String;)V
    aconst_null
    areturn
.end method

.method static sno_to_double(Ljava/lang/String;)D
    .limit stack 4
    .limit locals 1
    aload_0
    ifnull Lsno_pd_zero
    aload_0
    invokevirtual java/lang/String/trim()Ljava/lang/String;
    invokevirtual java/lang/String/isEmpty()Z
    ifne Lsno_pd_zero
    aload_0
    invokestatic java/lang/Double/parseDouble(Ljava/lang/String;)D
    dreturn
Lsno_pd_zero:
    dconst_0
    dreturn
.end method

.method static sno_str_eq(Ljava/lang/String;Ljava/lang/String;)Z
    .limit stack 4
    .limit locals 2
    aload_0
    ifnull Lstreq_false
    aload_1
    ifnull Lstreq_false
    aload_0
    aload_1
    invokevirtual java/lang/String/equalsIgnoreCase(Ljava/lang/String;)Z
    ireturn
Lstreq_false:
    iconst_0
    ireturn
.end method

.method static sno_kw_get(Ljava/lang/String;)Ljava/lang/String;
    .limit stack 4
    .limit locals 3
    aload_0
    ldc "ALPHABET"
    invokevirtual java/lang/String/equalsIgnoreCase(Ljava/lang/String;)Z
    ifeq Lkwg_not_alphabet
    new java/lang/StringBuilder
    dup
    invokespecial java/lang/StringBuilder/<init>()V
    astore_1
    iconst_0
    istore_2
Lkwg_alpha_loop:
    iload_2
    sipush 256
    if_icmpge Lkwg_alpha_done
    aload_1
    iload_2
    i2c
    invokevirtual java/lang/StringBuilder/append(C)Ljava/lang/StringBuilder;
    pop
    iinc 2 1
    goto Lkwg_alpha_loop
Lkwg_alpha_done:
    aload_1
    invokevirtual java/lang/StringBuilder/toString()Ljava/lang/String;
    areturn
Lkwg_not_alphabet:
    aload_0
    ldc "UCASE"
    invokevirtual java/lang/String/equalsIgnoreCase(Ljava/lang/String;)Z
    ifeq Lkwg_not_ucase
    ldc "ABCDEFGHIJKLMNOPQRSTUVWXYZ"
    areturn
Lkwg_not_ucase:
    aload_0
    ldc "LCASE"
    invokevirtual java/lang/String/equalsIgnoreCase(Ljava/lang/String;)Z
    ifeq Lkwg_not_lcase
    ldc "abcdefghijklmnopqrstuvwxyz"
    areturn
Lkwg_not_lcase:
    aload_0
    ldc "STNO"
    invokevirtual java/lang/String/equalsIgnoreCase(Ljava/lang/String;)Z
    ifeq Lkwg_not_stno
    getstatic expr_eval/sno_kw_STNO I
    invokestatic java/lang/Integer/toString(I)Ljava/lang/String;
    areturn
Lkwg_not_stno:
    aload_0
    ldc "TRIM"
    invokevirtual java/lang/String/equalsIgnoreCase(Ljava/lang/String;)Z
    ifeq Lkwg_not_trim
    getstatic expr_eval/sno_kw_TRIM I
    invokestatic java/lang/Integer/toString(I)Ljava/lang/String;
    areturn
Lkwg_not_trim:
    aload_0
    ldc "ANCHOR"
    invokevirtual java/lang/String/equalsIgnoreCase(Ljava/lang/String;)Z
    ifeq Lkwg_not_anchor
    getstatic expr_eval/sno_kw_ANCHOR I
    invokestatic java/lang/Integer/toString(I)Ljava/lang/String;
    areturn
Lkwg_not_anchor:
    aload_0
    ldc "STLIMIT"
    invokevirtual java/lang/String/equalsIgnoreCase(Ljava/lang/String;)Z
    ifeq Lkwg_not_stlimit
    getstatic expr_eval/sno_kw_STLIMIT I
    invokestatic java/lang/Integer/toString(I)Ljava/lang/String;
    areturn
Lkwg_not_stlimit:
    aload_0
    ldc "STCOUNT"
    invokevirtual java/lang/String/equalsIgnoreCase(Ljava/lang/String;)Z
    ifeq Lkwg_not_stcount
    getstatic expr_eval/sno_kw_STCOUNT I
    invokestatic java/lang/Integer/toString(I)Ljava/lang/String;
    areturn
Lkwg_not_stcount:
    ldc ""
    areturn
.end method

.method static sno_kw_set(Ljava/lang/String;Ljava/lang/String;)V
    .limit stack 4
    .limit locals 2
    aload_0
    ldc "TRIM"
    invokevirtual java/lang/String/equalsIgnoreCase(Ljava/lang/String;)Z
    ifeq Lkws_not_trim
    aload_1
    invokestatic java/lang/Integer/parseInt(Ljava/lang/String;)I
    putstatic expr_eval/sno_kw_TRIM I
    return
Lkws_not_trim:
    aload_0
    ldc "ANCHOR"
    invokevirtual java/lang/String/equalsIgnoreCase(Ljava/lang/String;)Z
    ifeq Lkws_not_anchor
    aload_1
    invokestatic java/lang/Integer/parseInt(Ljava/lang/String;)I
    putstatic expr_eval/sno_kw_ANCHOR I
    return
Lkws_not_anchor:
    aload_0
    ldc "STNO"
    invokevirtual java/lang/String/equalsIgnoreCase(Ljava/lang/String;)Z
    ifeq Lkws_not_stno
    aload_1
    invokestatic java/lang/Integer/parseInt(Ljava/lang/String;)I
    putstatic expr_eval/sno_kw_STNO I
    return
Lkws_not_stno:
    aload_0
    ldc "STLIMIT"
    invokevirtual java/lang/String/equalsIgnoreCase(Ljava/lang/String;)Z
    ifeq Lkws_not_stlimit
    aload_1
    invokestatic java/lang/Integer/parseInt(Ljava/lang/String;)I
    putstatic expr_eval/sno_kw_STLIMIT I
    return
Lkws_not_stlimit:
    aload_0
    ldc "STCOUNT"
    invokevirtual java/lang/String/equalsIgnoreCase(Ljava/lang/String;)Z
    ifeq Lkws_not_stcount
    aload_1
    invokestatic java/lang/Integer/parseInt(Ljava/lang/String;)I
    putstatic expr_eval/sno_kw_STCOUNT I
    return
Lkws_not_stcount:
    return
.end method

.method static sno_var_put(Ljava/lang/String;Ljava/lang/String;)V
    .limit stack 4
    .limit locals 2
    aload_0
    ldc "OUTPUT"
    invokevirtual java/lang/String/equalsIgnoreCase(Ljava/lang/String;)Z
    ifeq Lsvp_not_output
    getstatic expr_eval/sno_stdout Ljava/io/PrintStream;
    aload_1
    invokevirtual java/io/PrintStream/println(Ljava/lang/String;)V
    return
Lsvp_not_output:
    getstatic expr_eval/sno_vars Ljava/util/HashMap;
    aload_0
    aload_1
    invokevirtual java/util/HashMap/put(Ljava/lang/Object;Ljava/lang/Object;)Ljava/lang/Object;
    pop
    aload_0
    aload_1
    invokestatic expr_eval/sno_mon_var(Ljava/lang/String;Ljava/lang/String;)V
    return
.end method

.method static sno_mon_var(Ljava/lang/String;Ljava/lang/String;)V
    .limit stack 6
    .limit locals 3
    getstatic expr_eval/sno_mon_fd Ljava/io/OutputStream;
    ifnull Lsmv_done
    new java/lang/StringBuilder
    dup
    invokespecial java/lang/StringBuilder/<init>()V
    ldc "VALUE"
    invokevirtual java/lang/StringBuilder/append(Ljava/lang/String;)Ljava/lang/StringBuilder;
    bipush 30
    invokevirtual java/lang/StringBuilder/append(C)Ljava/lang/StringBuilder;
    aload_0
    invokevirtual java/lang/StringBuilder/append(Ljava/lang/String;)Ljava/lang/StringBuilder;
    bipush 31
    invokevirtual java/lang/StringBuilder/append(C)Ljava/lang/StringBuilder;
    aload_1
    invokevirtual java/lang/StringBuilder/append(Ljava/lang/String;)Ljava/lang/StringBuilder;
    bipush 30
    invokevirtual java/lang/StringBuilder/append(C)Ljava/lang/StringBuilder;
    invokevirtual java/lang/StringBuilder/toString()Ljava/lang/String;
    ldc "UTF-8"
    invokevirtual java/lang/String/getBytes(Ljava/lang/String;)[B
    astore_2
    getstatic expr_eval/sno_mon_fd Ljava/io/OutputStream;
    aload_2
    invokevirtual java/io/OutputStream/write([B)V
    getstatic expr_eval/sno_mon_go_fd Ljava/io/InputStream;
    ifnull Lsmv_done
    getstatic expr_eval/sno_mon_go_fd Ljava/io/InputStream;
    invokevirtual java/io/InputStream/read()I
    istore_2
    iload_2
    bipush 71
    if_icmpeq Lsmv_done
    iconst_0
    invokestatic SnoRuntime/sno_exit(I)V
Lsmv_done:
    return
.end method

.method static sno_stcount_tick()V
    .limit stack 4
    .limit locals 0
    getstatic expr_eval/sno_kw_STCOUNT I
    iconst_1
    iadd
    putstatic expr_eval/sno_kw_STCOUNT I
    getstatic expr_eval/sno_kw_STLIMIT I
    iflt Lstick_ok
    getstatic expr_eval/sno_kw_STCOUNT I
    getstatic expr_eval/sno_kw_STLIMIT I
    if_icmple Lstick_ok
    getstatic java/lang/System/err Ljava/io/PrintStream;
    ldc "Termination: statement limit"
    invokevirtual java/io/PrintStream/println(Ljava/lang/String;)V
    iconst_1
    invokestatic SnoRuntime/sno_exit(I)V
Lstick_ok:
    return
.end method

.method static sno_indr_get(Ljava/lang/String;)Ljava/lang/String;
    .limit stack 4
    .limit locals 1
    getstatic expr_eval/sno_vars Ljava/util/HashMap;
    aload_0
    invokevirtual java/util/HashMap/get(Ljava/lang/Object;)Ljava/lang/Object;
    checkcast java/lang/String
    dup
    ifnonnull Lsig_done_indr
    pop
    ldc ""
Lsig_done_indr:
    areturn
.end method

.method static sno_indr_set(Ljava/lang/String;Ljava/lang/String;)V
    .limit stack 4
    .limit locals 2
    getstatic expr_eval/sno_vars Ljava/util/HashMap;
    aload_0
    aload_1
    invokevirtual java/util/HashMap/put(Ljava/lang/Object;Ljava/lang/Object;)Ljava/lang/Object;
    pop
    return
.end method

.method static sno_input_read()Ljava/lang/String;
    .limit stack 6
    .limit locals 1
    getstatic       expr_eval/sno_input_br Ljava/io/BufferedReader;
    ifnonnull       Lir_ready
    new             java/io/BufferedReader
    dup
    new             java/io/InputStreamReader
    dup
    getstatic       java/lang/System/in Ljava/io/InputStream;
    invokespecial   java/io/InputStreamReader/<init>(Ljava/io/InputStream;)V
    invokespecial   java/io/BufferedReader/<init>(Ljava/io/Reader;)V
    putstatic       expr_eval/sno_input_br Ljava/io/BufferedReader;
Lir_ready:
    getstatic       expr_eval/sno_input_br Ljava/io/BufferedReader;
    invokevirtual   java/io/BufferedReader/readLine()Ljava/lang/String;
    areturn
.end method

.method static sno_array_new(Ljava/lang/String;)Ljava/lang/String;
    .limit stack 6
    .limit locals 2
    new java/util/HashMap
    dup
    invokespecial java/util/HashMap/<init>()V
    astore_1
    aload_1
    invokestatic java/lang/System/identityHashCode(Ljava/lang/Object;)I
    invokestatic java/lang/Integer/toString(I)Ljava/lang/String;
    dup
    getstatic expr_eval/sno_arrays Ljava/util/HashMap;
    swap
    aload_1
    invokevirtual java/util/HashMap/put(Ljava/lang/Object;Ljava/lang/Object;)Ljava/lang/Object;
    pop
    areturn
.end method

.method static sno_array_new2(Ljava/lang/String;Ljava/lang/String;)Ljava/lang/String;
    .limit stack 8
    .limit locals 6
    new java/util/HashMap
    dup
    invokespecial java/util/HashMap/<init>()V
    astore_2
    aload_2
    invokestatic java/lang/System/identityHashCode(Ljava/lang/Object;)I
    invokestatic java/lang/Integer/toString(I)Ljava/lang/String;
    astore_3
    getstatic expr_eval/sno_arrays Ljava/util/HashMap;
    aload_3
    aload_2
    invokevirtual java/util/HashMap/put(Ljava/lang/Object;Ljava/lang/Object;)Ljava/lang/Object;
    pop
    aload_0
    invokestatic java/lang/Double/parseDouble(Ljava/lang/String;)D
    d2i
    istore 4
    aload_1
    invokevirtual java/lang/String/isEmpty()Z
    ifne La2_done
    iconst_1
    istore 5
La2_loop:
    iload 5
    iload 4
    if_icmpgt La2_done
    aload_2
    iload 5
    invokestatic java/lang/Integer/toString(I)Ljava/lang/String;
    aload_1
    invokevirtual java/util/HashMap/put(Ljava/lang/Object;Ljava/lang/Object;)Ljava/lang/Object;
    pop
    iinc 5 1
    goto La2_loop
La2_done:
    aload_3
    areturn
.end method

.method static sno_table_new()Ljava/lang/String;
    .limit stack 6
    .limit locals 2
    new java/util/HashMap
    dup
    invokespecial java/util/HashMap/<init>()V
    astore_0
    aload_0
    invokestatic java/lang/System/identityHashCode(Ljava/lang/Object;)I
    invokestatic java/lang/Integer/toString(I)Ljava/lang/String;
    dup
    getstatic expr_eval/sno_arrays Ljava/util/HashMap;
    swap
    aload_0
    invokevirtual java/util/HashMap/put(Ljava/lang/Object;Ljava/lang/Object;)Ljava/lang/Object;
    pop
    areturn
.end method

.method static sno_array_get(Ljava/lang/String;Ljava/lang/String;)Ljava/lang/String;
    .limit stack 4
    .limit locals 3
    getstatic expr_eval/sno_arrays Ljava/util/HashMap;
    aload_0
    invokevirtual java/util/HashMap/get(Ljava/lang/Object;)Ljava/lang/Object;
    checkcast java/util/HashMap
    astore_2
    aload_2
    ifnull Lag_null
    aload_2
    aload_1
    invokevirtual java/util/HashMap/get(Ljava/lang/Object;)Ljava/lang/Object;
    checkcast java/lang/String
    areturn
Lag_null:
    aconst_null
    areturn
.end method

.method static sno_array_put(Ljava/lang/String;Ljava/lang/String;Ljava/lang/String;)V
    .limit stack 4
    .limit locals 4
    getstatic expr_eval/sno_arrays Ljava/util/HashMap;
    aload_0
    invokevirtual java/util/HashMap/get(Ljava/lang/Object;)Ljava/lang/Object;
    checkcast java/util/HashMap
    astore_3
    aload_3
    ifnull Lap_done
    aload_3
    aload_1
    aload_2
    invokevirtual java/util/HashMap/put(Ljava/lang/Object;Ljava/lang/Object;)Ljava/lang/Object;
    pop
Lap_done:
    return
.end method

