; Generated by scrip-cc -jvm
; Assemble: java -jar jasmin.jar <file>.j -d .
; Run:      java <classname>

.class public _012_func_locals
.super java/lang/Object

; Runtime fields
.field static sno_stdout Ljava/io/PrintStream;
.field static sno_input_br Ljava/io/BufferedReader;
.field static sno_kw_TRIM I
.field static sno_kw_ANCHOR I
.field static sno_kw_STNO I
.field static sno_kw_STLIMIT I
.field static sno_kw_STCOUNT I
.field static sno_vars Ljava/util/HashMap;
.field static sno_arrays Ljava/util/HashMap;
.field static sno_data_types Ljava/util/HashMap;
.field static sno_mon_fd Ljava/io/OutputStream;
.field static sno_mon_go_fd Ljava/io/InputStream;
.field static sno_var_a Ljava/lang/String;
.field static sno_var_b Ljava/lang/String;
.field static sno_var_d Ljava/lang/String;
.field static sno_var_lfunc Ljava/lang/String;
.field static sno_var_checklocal Ljava/lang/String;

.method static <clinit>()V
    .limit stack 19
    .limit locals 0
    getstatic       java/lang/System/out Ljava/io/PrintStream;
    putstatic       _012_func_locals/sno_stdout Ljava/io/PrintStream;
    iconst_0
    putstatic       _012_func_locals/sno_kw_TRIM I
    iconst_0
    putstatic       _012_func_locals/sno_kw_ANCHOR I
    iconst_0
    putstatic       _012_func_locals/sno_kw_STNO I
    iconst_m1
    putstatic       _012_func_locals/sno_kw_STLIMIT I
    iconst_0
    putstatic       _012_func_locals/sno_kw_STCOUNT I
    new java/util/HashMap
    dup
    invokespecial java/util/HashMap/<init>()V
    putstatic       _012_func_locals/sno_vars Ljava/util/HashMap;
    new java/util/HashMap
    dup
    invokespecial java/util/HashMap/<init>()V
    putstatic       _012_func_locals/sno_arrays Ljava/util/HashMap;
    new java/util/HashMap
    dup
    invokespecial java/util/HashMap/<init>()V
    putstatic       _012_func_locals/sno_data_types Ljava/util/HashMap;
    ldc             ""
    putstatic       _012_func_locals/sno_var_a Ljava/lang/String;
    getstatic       _012_func_locals/sno_vars Ljava/util/HashMap;
    ldc             "a"
    ldc             ""
    invokevirtual   java/util/HashMap/put(Ljava/lang/Object;Ljava/lang/Object;)Ljava/lang/Object;
    pop
    ldc             ""
    putstatic       _012_func_locals/sno_var_b Ljava/lang/String;
    getstatic       _012_func_locals/sno_vars Ljava/util/HashMap;
    ldc             "b"
    ldc             ""
    invokevirtual   java/util/HashMap/put(Ljava/lang/Object;Ljava/lang/Object;)Ljava/lang/Object;
    pop
    ldc             ""
    putstatic       _012_func_locals/sno_var_d Ljava/lang/String;
    getstatic       _012_func_locals/sno_vars Ljava/util/HashMap;
    ldc             "d"
    ldc             ""
    invokevirtual   java/util/HashMap/put(Ljava/lang/Object;Ljava/lang/Object;)Ljava/lang/Object;
    pop
    ldc             ""
    putstatic       _012_func_locals/sno_var_lfunc Ljava/lang/String;
    getstatic       _012_func_locals/sno_vars Ljava/util/HashMap;
    ldc             "lfunc"
    ldc             ""
    invokevirtual   java/util/HashMap/put(Ljava/lang/Object;Ljava/lang/Object;)Ljava/lang/Object;
    pop
    ldc             ""
    putstatic       _012_func_locals/sno_var_checklocal Ljava/lang/String;
    getstatic       _012_func_locals/sno_vars Ljava/util/HashMap;
    ldc             "checklocal"
    ldc             ""
    invokevirtual   java/util/HashMap/put(Ljava/lang/Object;Ljava/lang/Object;)Ljava/lang/Object;
    pop
    return
.end method

.method static sno_mon_init()V
    .limit stack 6
    .limit locals 2
    ldc "MONITOR_READY_PIPE"
    invokestatic java/lang/System/getenv(Ljava/lang/String;)Ljava/lang/String;
    astore_0
    aload_0
    ifnull Lsmi_done
    aload_0
    invokevirtual java/lang/String/isEmpty()Z
    ifne Lsmi_done
    new java/io/FileOutputStream
    dup
    aload_0
    iconst_1
    invokespecial java/io/FileOutputStream/<init>(Ljava/lang/String;Z)V
    putstatic _012_func_locals/sno_mon_fd Ljava/io/OutputStream;
    ldc "MONITOR_GO_PIPE"
    invokestatic java/lang/System/getenv(Ljava/lang/String;)Ljava/lang/String;
    astore_1
    aload_1
    ifnull Lsmi_done
    aload_1
    invokevirtual java/lang/String/isEmpty()Z
    ifne Lsmi_done
    new java/io/FileInputStream
    dup
    aload_1
    invokespecial java/io/FileInputStream/<init>(Ljava/lang/String;)V
    putstatic _012_func_locals/sno_mon_go_fd Ljava/io/InputStream;
Lsmi_done:
    return
.end method

.method public static main([Ljava/lang/String;)V
    .limit stack 16
    .limit locals 32

    invokestatic _012_func_locals/sno_mon_init()V
    getstatic _012_func_locals/sno_kw_STNO I
    iconst_1
    iadd
    putstatic _012_func_locals/sno_kw_STNO I
    invokestatic _012_func_locals/sno_stcount_tick()V
    ldc ""
    pop
    goto L_lfunc_end
; === lfunc_end =======================================================
L_lfunc_end:
    getstatic _012_func_locals/sno_kw_STNO I
    iconst_1
    iadd
    putstatic _012_func_locals/sno_kw_STNO I
    invokestatic _012_func_locals/sno_stcount_tick()V
    ldc "global_a"
    dup
    ifnonnull Lvar_ok_0
    pop
    goto Lvar_fail_0
Lvar_ok_0:
    ldc "a"
    swap
    invokestatic _012_func_locals/sno_var_put(Ljava/lang/String;Ljava/lang/String;)V
Lvar_fail_0:
    getstatic _012_func_locals/sno_kw_STNO I
    iconst_1
    iadd
    putstatic _012_func_locals/sno_kw_STNO I
    invokestatic _012_func_locals/sno_stcount_tick()V
    ldc "global_d"
    dup
    ifnonnull Lvar_ok_1
    pop
    goto Lvar_fail_1
Lvar_ok_1:
    ldc "d"
    swap
    invokestatic _012_func_locals/sno_var_put(Ljava/lang/String;Ljava/lang/String;)V
Lvar_fail_1:
    getstatic _012_func_locals/sno_kw_STNO I
    iconst_1
    iadd
    putstatic _012_func_locals/sno_kw_STNO I
    invokestatic _012_func_locals/sno_stcount_tick()V
    ldc "p"
    ldc "q"
    ldc "r"
    invokestatic _012_func_locals/sno_userfn_lfunc(Ljava/lang/String;Ljava/lang/String;Ljava/lang/String;)Ljava/lang/String;
    dup
    ifnonnull Ldiff_n0_0
    pop
    ldc ""
Ldiff_n0_0:
    ldc "aabbdd"
    dup
    ifnonnull Ldiff_n1_0
    pop
    ldc ""
Ldiff_n1_0:
    invokevirtual java/lang/String/equals(Ljava/lang/Object;)Z
    ifne Ldiff_f_0
    ldc ""
    goto Ldiff_d_0
Ldiff_f_0:
    aconst_null
Ldiff_d_0:
    dup
    ifnonnull Lef_nn_0
    pop
    goto L_e004
Lef_nn_0:
    pop
Lef_dn_0:
    getstatic _012_func_locals/sno_kw_STNO I
    iconst_1
    iadd
    putstatic _012_func_locals/sno_kw_STNO I
    invokestatic _012_func_locals/sno_stcount_tick()V
    ldc "FAIL 1012/004: lfunc return value"
    dup
    ifnonnull Lout_ok_0
    pop
    goto Lout_fail_0
Lout_ok_0:
    getstatic _012_func_locals/sno_stdout Ljava/io/PrintStream;
    swap
    invokevirtual java/io/PrintStream/println(Ljava/lang/String;)V
    goto L_END
Lout_fail_0:
    goto L_END
; === e004 ============================================================
L_e004:
    getstatic _012_func_locals/sno_kw_STNO I
    iconst_1
    iadd
    putstatic _012_func_locals/sno_kw_STNO I
    invokestatic _012_func_locals/sno_stcount_tick()V
    ldc "a"
    invokestatic _012_func_locals/sno_indr_get(Ljava/lang/String;)Ljava/lang/String;
    dup
    ifnonnull Lident_n_0
    pop
    ldc ""
Lident_n_0:
    ldc "global_a"
    dup
    ifnonnull Lident_n2_0
    pop
    ldc ""
Lident_n2_0:
    invokevirtual java/lang/String/equals(Ljava/lang/Object;)Z
    ifeq Lident_f_0
    ldc "a"
    invokestatic _012_func_locals/sno_indr_get(Ljava/lang/String;)Ljava/lang/String;
    dup
    ifnonnull Lident_n3_0
    pop
    ldc ""
Lident_n3_0:
    goto Lident_d_0
Lident_f_0:
    aconst_null
Lident_d_0:
    dup
    ifnonnull Lef_nn_1
    pop
    goto Lef_dn_1
Lef_nn_1:
    pop
    goto L_e005
Lef_dn_1:
    getstatic _012_func_locals/sno_kw_STNO I
    iconst_1
    iadd
    putstatic _012_func_locals/sno_kw_STNO I
    invokestatic _012_func_locals/sno_stcount_tick()V
    ldc "FAIL 1012/005: global a not clobbered"
    dup
    ifnonnull Lout_ok_1
    pop
    goto Lout_fail_1
Lout_ok_1:
    getstatic _012_func_locals/sno_stdout Ljava/io/PrintStream;
    swap
    invokevirtual java/io/PrintStream/println(Ljava/lang/String;)V
    goto L_END
Lout_fail_1:
    goto L_END
; === e005 ============================================================
L_e005:
    getstatic _012_func_locals/sno_kw_STNO I
    iconst_1
    iadd
    putstatic _012_func_locals/sno_kw_STNO I
    invokestatic _012_func_locals/sno_stcount_tick()V
    ldc "d"
    invokestatic _012_func_locals/sno_indr_get(Ljava/lang/String;)Ljava/lang/String;
    dup
    ifnonnull Lident_n_1
    pop
    ldc ""
Lident_n_1:
    ldc "global_d"
    dup
    ifnonnull Lident_n2_1
    pop
    ldc ""
Lident_n2_1:
    invokevirtual java/lang/String/equals(Ljava/lang/Object;)Z
    ifeq Lident_f_1
    ldc "d"
    invokestatic _012_func_locals/sno_indr_get(Ljava/lang/String;)Ljava/lang/String;
    dup
    ifnonnull Lident_n3_1
    pop
    ldc ""
Lident_n3_1:
    goto Lident_d_1
Lident_f_1:
    aconst_null
Lident_d_1:
    dup
    ifnonnull Lef_nn_2
    pop
    goto Lef_dn_2
Lef_nn_2:
    pop
    goto L_e006
Lef_dn_2:
    getstatic _012_func_locals/sno_kw_STNO I
    iconst_1
    iadd
    putstatic _012_func_locals/sno_kw_STNO I
    invokestatic _012_func_locals/sno_stcount_tick()V
    ldc "FAIL 1012/006: global d not clobbered"
    dup
    ifnonnull Lout_ok_2
    pop
    goto Lout_fail_2
Lout_ok_2:
    getstatic _012_func_locals/sno_stdout Ljava/io/PrintStream;
    swap
    invokevirtual java/io/PrintStream/println(Ljava/lang/String;)V
    goto L_END
Lout_fail_2:
    goto L_END
; === e006 ============================================================
L_e006:
    getstatic _012_func_locals/sno_kw_STNO I
    iconst_1
    iadd
    putstatic _012_func_locals/sno_kw_STNO I
    invokestatic _012_func_locals/sno_stcount_tick()V
    ldc ""
    pop
    goto L_cl_end
; === cl_end ==========================================================
L_cl_end:
    getstatic _012_func_locals/sno_kw_STNO I
    iconst_1
    iadd
    putstatic _012_func_locals/sno_kw_STNO I
    invokestatic _012_func_locals/sno_stcount_tick()V
    invokestatic _012_func_locals/sno_userfn_checklocal()Ljava/lang/String;
    dup
    ifnonnull Ldiff_n0_1
    pop
    ldc ""
Ldiff_n0_1:
    ldc ""
    invokevirtual java/lang/String/equals(Ljava/lang/Object;)Z
    ifne Ldiff_f_1
    ldc ""
    goto Ldiff_d_1
Ldiff_f_1:
    aconst_null
Ldiff_d_1:
    dup
    ifnonnull Lef_nn_3
    pop
    goto L_e007
Lef_nn_3:
    pop
Lef_dn_3:
    getstatic _012_func_locals/sno_kw_STNO I
    iconst_1
    iadd
    putstatic _012_func_locals/sno_kw_STNO I
    invokestatic _012_func_locals/sno_stcount_tick()V
    ldc "FAIL 1012/007: local null on fresh call"
    dup
    ifnonnull Lout_ok_3
    pop
    goto Lout_fail_3
Lout_ok_3:
    getstatic _012_func_locals/sno_stdout Ljava/io/PrintStream;
    swap
    invokevirtual java/io/PrintStream/println(Ljava/lang/String;)V
    goto L_END
Lout_fail_3:
    goto L_END
; === e007 ============================================================
L_e007:
    getstatic _012_func_locals/sno_kw_STNO I
    iconst_1
    iadd
    putstatic _012_func_locals/sno_kw_STNO I
    invokestatic _012_func_locals/sno_stcount_tick()V
    ldc "PASS 1012_func_locals (7/7)"
    dup
    ifnonnull Lout_ok_4
    pop
    goto Lout_fail_4
Lout_ok_4:
    getstatic _012_func_locals/sno_stdout Ljava/io/PrintStream;
    swap
    invokevirtual java/io/PrintStream/println(Ljava/lang/String;)V
Lout_fail_4:
; === END =============================================================
L_END:
    nop
; program end
    return
.end method
.method static sno_userfn_lfunc(Ljava/lang/String;Ljava/lang/String;Ljava/lang/String;)Ljava/lang/String;
    .limit stack 16
    .limit locals 64

    ldc "a"
    invokestatic _012_func_locals/sno_indr_get(Ljava/lang/String;)Ljava/lang/String;
    astore 3
    ldc "b"
    invokestatic _012_func_locals/sno_indr_get(Ljava/lang/String;)Ljava/lang/String;
    astore 4
    ldc "c"
    invokestatic _012_func_locals/sno_indr_get(Ljava/lang/String;)Ljava/lang/String;
    astore 5
    ldc "d"
    invokestatic _012_func_locals/sno_indr_get(Ljava/lang/String;)Ljava/lang/String;
    astore 6
    ldc "e"
    invokestatic _012_func_locals/sno_indr_get(Ljava/lang/String;)Ljava/lang/String;
    astore 7
    ldc "f"
    invokestatic _012_func_locals/sno_indr_get(Ljava/lang/String;)Ljava/lang/String;
    astore 8
    ldc "lfunc"
    invokestatic _012_func_locals/sno_indr_get(Ljava/lang/String;)Ljava/lang/String;
    astore 9
    ldc "a"
    aload 0
    invokestatic _012_func_locals/sno_var_put(Ljava/lang/String;Ljava/lang/String;)V
    ldc "b"
    aload 1
    invokestatic _012_func_locals/sno_var_put(Ljava/lang/String;Ljava/lang/String;)V
    ldc "c"
    aload 2
    invokestatic _012_func_locals/sno_var_put(Ljava/lang/String;Ljava/lang/String;)V
    ldc "d"
    ldc ""
    invokestatic _012_func_locals/sno_var_put(Ljava/lang/String;Ljava/lang/String;)V
    ldc "e"
    ldc ""
    invokestatic _012_func_locals/sno_var_put(Ljava/lang/String;Ljava/lang/String;)V
    ldc "f"
    ldc ""
    invokestatic _012_func_locals/sno_var_put(Ljava/lang/String;Ljava/lang/String;)V
    ldc "lfunc"
    ldc ""
    invokestatic _012_func_locals/sno_var_put(Ljava/lang/String;Ljava/lang/String;)V
; === lfunc ===========================================================
Lf0_lfunc:
    getstatic _012_func_locals/sno_kw_STNO I
    iconst_1
    iadd
    putstatic _012_func_locals/sno_kw_STNO I
    invokestatic _012_func_locals/sno_stcount_tick()V
    ldc "a"
    invokestatic _012_func_locals/sno_indr_get(Ljava/lang/String;)Ljava/lang/String;
    dup
    ifnonnull Lident_n_2
    pop
    ldc ""
Lident_n_2:
    ldc "p"
    dup
    ifnonnull Lident_n2_2
    pop
    ldc ""
Lident_n2_2:
    invokevirtual java/lang/String/equals(Ljava/lang/Object;)Z
    ifeq Lident_f_2
    ldc "a"
    invokestatic _012_func_locals/sno_indr_get(Ljava/lang/String;)Ljava/lang/String;
    dup
    ifnonnull Lident_n3_2
    pop
    ldc ""
Lident_n3_2:
    goto Lident_d_2
Lident_f_2:
    aconst_null
Lident_d_2:
    dup
    ifnonnull Lef_nn_4
    pop
    goto Lef_dn_4
Lef_nn_4:
    pop
    goto Lf0_e001
Lef_dn_4:
    getstatic _012_func_locals/sno_kw_STNO I
    iconst_1
    iadd
    putstatic _012_func_locals/sno_kw_STNO I
    invokestatic _012_func_locals/sno_stcount_tick()V
    ldc "FAIL 1012/001: arg a should be p"
    dup
    ifnonnull Lout_ok_5
    pop
    goto Lout_fail_5
Lout_ok_5:
    getstatic _012_func_locals/sno_stdout Ljava/io/PrintStream;
    swap
    invokevirtual java/io/PrintStream/println(Ljava/lang/String;)V
    goto L_END
Lout_fail_5:
    goto L_END
; === e001 ============================================================
Lf0_e001:
    getstatic _012_func_locals/sno_kw_STNO I
    iconst_1
    iadd
    putstatic _012_func_locals/sno_kw_STNO I
    invokestatic _012_func_locals/sno_stcount_tick()V
    ldc "b"
    invokestatic _012_func_locals/sno_indr_get(Ljava/lang/String;)Ljava/lang/String;
    dup
    ifnonnull Lident_n_3
    pop
    ldc ""
Lident_n_3:
    ldc "q"
    dup
    ifnonnull Lident_n2_3
    pop
    ldc ""
Lident_n2_3:
    invokevirtual java/lang/String/equals(Ljava/lang/Object;)Z
    ifeq Lident_f_3
    ldc "b"
    invokestatic _012_func_locals/sno_indr_get(Ljava/lang/String;)Ljava/lang/String;
    dup
    ifnonnull Lident_n3_3
    pop
    ldc ""
Lident_n3_3:
    goto Lident_d_3
Lident_f_3:
    aconst_null
Lident_d_3:
    dup
    ifnonnull Lef_nn_5
    pop
    goto Lef_dn_5
Lef_nn_5:
    pop
    goto Lf0_e002
Lef_dn_5:
    getstatic _012_func_locals/sno_kw_STNO I
    iconst_1
    iadd
    putstatic _012_func_locals/sno_kw_STNO I
    invokestatic _012_func_locals/sno_stcount_tick()V
    ldc "FAIL 1012/002: arg b should be q"
    dup
    ifnonnull Lout_ok_6
    pop
    goto Lout_fail_6
Lout_ok_6:
    getstatic _012_func_locals/sno_stdout Ljava/io/PrintStream;
    swap
    invokevirtual java/io/PrintStream/println(Ljava/lang/String;)V
    goto L_END
Lout_fail_6:
    goto L_END
; === e002 ============================================================
Lf0_e002:
    getstatic _012_func_locals/sno_kw_STNO I
    iconst_1
    iadd
    putstatic _012_func_locals/sno_kw_STNO I
    invokestatic _012_func_locals/sno_stcount_tick()V
    ldc "d"
    invokestatic _012_func_locals/sno_indr_get(Ljava/lang/String;)Ljava/lang/String;
    dup
    ifnonnull Ldiff_n0_2
    pop
    ldc ""
Ldiff_n0_2:
    ldc ""
    invokevirtual java/lang/String/equals(Ljava/lang/Object;)Z
    ifne Ldiff_f_2
    ldc ""
    goto Ldiff_d_2
Ldiff_f_2:
    aconst_null
Ldiff_d_2:
    dup
    ifnonnull Lef_nn_6
    pop
    goto Lf0_e003
Lef_nn_6:
    pop
Lef_dn_6:
    getstatic _012_func_locals/sno_kw_STNO I
    iconst_1
    iadd
    putstatic _012_func_locals/sno_kw_STNO I
    invokestatic _012_func_locals/sno_stcount_tick()V
    ldc "FAIL 1012/003: local d should be null"
    dup
    ifnonnull Lout_ok_7
    pop
    goto Lout_fail_7
Lout_ok_7:
    getstatic _012_func_locals/sno_stdout Ljava/io/PrintStream;
    swap
    invokevirtual java/io/PrintStream/println(Ljava/lang/String;)V
    goto L_END
Lout_fail_7:
    goto L_END
; === e003 ============================================================
Lf0_e003:
    getstatic _012_func_locals/sno_kw_STNO I
    iconst_1
    iadd
    putstatic _012_func_locals/sno_kw_STNO I
    invokestatic _012_func_locals/sno_stcount_tick()V
    ldc "aa"
    dup
    ifnonnull Lvar_ok_2
    pop
    goto Lvar_fail_2
Lvar_ok_2:
    ldc "a"
    swap
    invokestatic _012_func_locals/sno_var_put(Ljava/lang/String;Ljava/lang/String;)V
Lvar_fail_2:
    getstatic _012_func_locals/sno_kw_STNO I
    iconst_1
    iadd
    putstatic _012_func_locals/sno_kw_STNO I
    invokestatic _012_func_locals/sno_stcount_tick()V
    ldc "bb"
    dup
    ifnonnull Lvar_ok_3
    pop
    goto Lvar_fail_3
Lvar_ok_3:
    ldc "b"
    swap
    invokestatic _012_func_locals/sno_var_put(Ljava/lang/String;Ljava/lang/String;)V
Lvar_fail_3:
    getstatic _012_func_locals/sno_kw_STNO I
    iconst_1
    iadd
    putstatic _012_func_locals/sno_kw_STNO I
    invokestatic _012_func_locals/sno_stcount_tick()V
    ldc "dd"
    dup
    ifnonnull Lvar_ok_4
    pop
    goto Lvar_fail_4
Lvar_ok_4:
    ldc "d"
    swap
    invokestatic _012_func_locals/sno_var_put(Ljava/lang/String;Ljava/lang/String;)V
Lvar_fail_4:
    getstatic _012_func_locals/sno_kw_STNO I
    iconst_1
    iadd
    putstatic _012_func_locals/sno_kw_STNO I
    invokestatic _012_func_locals/sno_stcount_tick()V
    new java/lang/StringBuilder
    dup
    invokespecial java/lang/StringBuilder/<init>()V
    ldc "a"
    invokestatic _012_func_locals/sno_indr_get(Ljava/lang/String;)Ljava/lang/String;
    dup
    ifnonnull Lconc_ok_0_0
    pop
    pop
    aconst_null
    goto Lconc_done_0
Lconc_ok_0_0:
    invokevirtual java/lang/StringBuilder/append(Ljava/lang/String;)Ljava/lang/StringBuilder;
    ldc "b"
    invokestatic _012_func_locals/sno_indr_get(Ljava/lang/String;)Ljava/lang/String;
    dup
    ifnonnull Lconc_ok_0_1
    pop
    pop
    aconst_null
    goto Lconc_done_0
Lconc_ok_0_1:
    invokevirtual java/lang/StringBuilder/append(Ljava/lang/String;)Ljava/lang/StringBuilder;
    ldc "d"
    invokestatic _012_func_locals/sno_indr_get(Ljava/lang/String;)Ljava/lang/String;
    dup
    ifnonnull Lconc_ok_0_2
    pop
    pop
    aconst_null
    goto Lconc_done_0
Lconc_ok_0_2:
    invokevirtual java/lang/StringBuilder/append(Ljava/lang/String;)Ljava/lang/StringBuilder;
    invokevirtual java/lang/StringBuilder/toString()Ljava/lang/String;
Lconc_done_0:
    dup
    ifnonnull Lvar_ok_5
    pop
    goto Lvar_fail_5
Lvar_ok_5:
    ldc "lfunc"
    swap
    invokestatic _012_func_locals/sno_var_put(Ljava/lang/String;Ljava/lang/String;)V
    goto Jfn0_return
Lvar_fail_5:
Jfn0_return:
    ldc "a"
    aload 3
    invokestatic _012_func_locals/sno_var_put(Ljava/lang/String;Ljava/lang/String;)V
    ldc "b"
    aload 4
    invokestatic _012_func_locals/sno_var_put(Ljava/lang/String;Ljava/lang/String;)V
    ldc "c"
    aload 5
    invokestatic _012_func_locals/sno_var_put(Ljava/lang/String;Ljava/lang/String;)V
    ldc "d"
    aload 6
    invokestatic _012_func_locals/sno_var_put(Ljava/lang/String;Ljava/lang/String;)V
    ldc "e"
    aload 7
    invokestatic _012_func_locals/sno_var_put(Ljava/lang/String;Ljava/lang/String;)V
    ldc "f"
    aload 8
    invokestatic _012_func_locals/sno_var_put(Ljava/lang/String;Ljava/lang/String;)V
    ldc "lfunc"
    invokestatic _012_func_locals/sno_indr_get(Ljava/lang/String;)Ljava/lang/String;
    ldc "lfunc"
    aload 9
    invokestatic _012_func_locals/sno_var_put(Ljava/lang/String;Ljava/lang/String;)V
    areturn
Jfn0_freturn:
    ldc "a"
    aload 3
    invokestatic _012_func_locals/sno_var_put(Ljava/lang/String;Ljava/lang/String;)V
    ldc "b"
    aload 4
    invokestatic _012_func_locals/sno_var_put(Ljava/lang/String;Ljava/lang/String;)V
    ldc "c"
    aload 5
    invokestatic _012_func_locals/sno_var_put(Ljava/lang/String;Ljava/lang/String;)V
    ldc "d"
    aload 6
    invokestatic _012_func_locals/sno_var_put(Ljava/lang/String;Ljava/lang/String;)V
    ldc "e"
    aload 7
    invokestatic _012_func_locals/sno_var_put(Ljava/lang/String;Ljava/lang/String;)V
    ldc "f"
    aload 8
    invokestatic _012_func_locals/sno_var_put(Ljava/lang/String;Ljava/lang/String;)V
    ldc "lfunc"
    aload 9
    invokestatic _012_func_locals/sno_var_put(Ljava/lang/String;Ljava/lang/String;)V
    aconst_null
    areturn
.end method

.method static sno_userfn_checklocal()Ljava/lang/String;
    .limit stack 16
    .limit locals 64

    ldc "x"
    invokestatic _012_func_locals/sno_indr_get(Ljava/lang/String;)Ljava/lang/String;
    astore 0
    ldc "checklocal"
    invokestatic _012_func_locals/sno_indr_get(Ljava/lang/String;)Ljava/lang/String;
    astore 1
    ldc "x"
    ldc ""
    invokestatic _012_func_locals/sno_var_put(Ljava/lang/String;Ljava/lang/String;)V
    ldc "checklocal"
    ldc ""
    invokestatic _012_func_locals/sno_var_put(Ljava/lang/String;Ljava/lang/String;)V
; === checklocal ======================================================
Lf1_checklocal:
    getstatic _012_func_locals/sno_kw_STNO I
    iconst_1
    iadd
    putstatic _012_func_locals/sno_kw_STNO I
    invokestatic _012_func_locals/sno_stcount_tick()V
    ldc "x"
    invokestatic _012_func_locals/sno_indr_get(Ljava/lang/String;)Ljava/lang/String;
    dup
    ifnonnull Ldiff_n0_3
    pop
    ldc ""
Ldiff_n0_3:
    ldc ""
    invokevirtual java/lang/String/equals(Ljava/lang/Object;)Z
    ifne Ldiff_f_3
    ldc ""
    goto Ldiff_d_3
Ldiff_f_3:
    aconst_null
Ldiff_d_3:
    dup
    ifnonnull Lef_nn_7
    pop
    goto Lf1_e007_inner
Lef_nn_7:
    pop
Lef_dn_7:
    getstatic _012_func_locals/sno_kw_STNO I
    iconst_1
    iadd
    putstatic _012_func_locals/sno_kw_STNO I
    invokestatic _012_func_locals/sno_stcount_tick()V
    ldc "local-not-null"
    dup
    ifnonnull Lvar_ok_6
    pop
    goto Lvar_fail_6
Lvar_ok_6:
    ldc "checklocal"
    swap
    invokestatic _012_func_locals/sno_var_put(Ljava/lang/String;Ljava/lang/String;)V
    goto Jfn1_return
Lvar_fail_6:
; === e007_inner ======================================================
Lf1_e007_inner:
    getstatic _012_func_locals/sno_kw_STNO I
    iconst_1
    iadd
    putstatic _012_func_locals/sno_kw_STNO I
    invokestatic _012_func_locals/sno_stcount_tick()V
    ldc "checklocal"
    ldc ""
    invokestatic _012_func_locals/sno_var_put(Ljava/lang/String;Ljava/lang/String;)V
    goto Jfn1_return
Jfn1_return:
    ldc "x"
    aload 0
    invokestatic _012_func_locals/sno_var_put(Ljava/lang/String;Ljava/lang/String;)V
    ldc "checklocal"
    invokestatic _012_func_locals/sno_indr_get(Ljava/lang/String;)Ljava/lang/String;
    ldc "checklocal"
    aload 1
    invokestatic _012_func_locals/sno_var_put(Ljava/lang/String;Ljava/lang/String;)V
    areturn
Jfn1_freturn:
    ldc "x"
    aload 0
    invokestatic _012_func_locals/sno_var_put(Ljava/lang/String;Ljava/lang/String;)V
    ldc "checklocal"
    aload 1
    invokestatic _012_func_locals/sno_var_put(Ljava/lang/String;Ljava/lang/String;)V
    aconst_null
    areturn
.end method

.method static sno_str_eq(Ljava/lang/String;Ljava/lang/String;)Z
    .limit stack 4
    .limit locals 2
    aload_0
    ifnull Lstreq_false
    aload_1
    ifnull Lstreq_false
    aload_0
    aload_1
    invokevirtual java/lang/String/equalsIgnoreCase(Ljava/lang/String;)Z
    ireturn
Lstreq_false:
    iconst_0
    ireturn
.end method

.method static sno_kw_get(Ljava/lang/String;)Ljava/lang/String;
    .limit stack 4
    .limit locals 3
    aload_0
    ldc "ALPHABET"
    invokevirtual java/lang/String/equalsIgnoreCase(Ljava/lang/String;)Z
    ifeq Lkwg_not_alphabet
    new java/lang/StringBuilder
    dup
    invokespecial java/lang/StringBuilder/<init>()V
    astore_1
    iconst_0
    istore_2
Lkwg_alpha_loop:
    iload_2
    sipush 256
    if_icmpge Lkwg_alpha_done
    aload_1
    iload_2
    i2c
    invokevirtual java/lang/StringBuilder/append(C)Ljava/lang/StringBuilder;
    pop
    iinc 2 1
    goto Lkwg_alpha_loop
Lkwg_alpha_done:
    aload_1
    invokevirtual java/lang/StringBuilder/toString()Ljava/lang/String;
    areturn
Lkwg_not_alphabet:
    aload_0
    ldc "UCASE"
    invokevirtual java/lang/String/equalsIgnoreCase(Ljava/lang/String;)Z
    ifeq Lkwg_not_ucase
    ldc "ABCDEFGHIJKLMNOPQRSTUVWXYZ"
    areturn
Lkwg_not_ucase:
    aload_0
    ldc "LCASE"
    invokevirtual java/lang/String/equalsIgnoreCase(Ljava/lang/String;)Z
    ifeq Lkwg_not_lcase
    ldc "abcdefghijklmnopqrstuvwxyz"
    areturn
Lkwg_not_lcase:
    aload_0
    ldc "STNO"
    invokevirtual java/lang/String/equalsIgnoreCase(Ljava/lang/String;)Z
    ifeq Lkwg_not_stno
    getstatic _012_func_locals/sno_kw_STNO I
    invokestatic java/lang/Integer/toString(I)Ljava/lang/String;
    areturn
Lkwg_not_stno:
    aload_0
    ldc "TRIM"
    invokevirtual java/lang/String/equalsIgnoreCase(Ljava/lang/String;)Z
    ifeq Lkwg_not_trim
    getstatic _012_func_locals/sno_kw_TRIM I
    invokestatic java/lang/Integer/toString(I)Ljava/lang/String;
    areturn
Lkwg_not_trim:
    aload_0
    ldc "ANCHOR"
    invokevirtual java/lang/String/equalsIgnoreCase(Ljava/lang/String;)Z
    ifeq Lkwg_not_anchor
    getstatic _012_func_locals/sno_kw_ANCHOR I
    invokestatic java/lang/Integer/toString(I)Ljava/lang/String;
    areturn
Lkwg_not_anchor:
    aload_0
    ldc "STLIMIT"
    invokevirtual java/lang/String/equalsIgnoreCase(Ljava/lang/String;)Z
    ifeq Lkwg_not_stlimit
    getstatic _012_func_locals/sno_kw_STLIMIT I
    invokestatic java/lang/Integer/toString(I)Ljava/lang/String;
    areturn
Lkwg_not_stlimit:
    aload_0
    ldc "STCOUNT"
    invokevirtual java/lang/String/equalsIgnoreCase(Ljava/lang/String;)Z
    ifeq Lkwg_not_stcount
    getstatic _012_func_locals/sno_kw_STCOUNT I
    invokestatic java/lang/Integer/toString(I)Ljava/lang/String;
    areturn
Lkwg_not_stcount:
    ldc ""
    areturn
.end method

.method static sno_kw_set(Ljava/lang/String;Ljava/lang/String;)V
    .limit stack 4
    .limit locals 2
    aload_0
    ldc "TRIM"
    invokevirtual java/lang/String/equalsIgnoreCase(Ljava/lang/String;)Z
    ifeq Lkws_not_trim
    aload_1
    invokestatic java/lang/Integer/parseInt(Ljava/lang/String;)I
    putstatic _012_func_locals/sno_kw_TRIM I
    return
Lkws_not_trim:
    aload_0
    ldc "ANCHOR"
    invokevirtual java/lang/String/equalsIgnoreCase(Ljava/lang/String;)Z
    ifeq Lkws_not_anchor
    aload_1
    invokestatic java/lang/Integer/parseInt(Ljava/lang/String;)I
    putstatic _012_func_locals/sno_kw_ANCHOR I
    return
Lkws_not_anchor:
    aload_0
    ldc "STNO"
    invokevirtual java/lang/String/equalsIgnoreCase(Ljava/lang/String;)Z
    ifeq Lkws_not_stno
    aload_1
    invokestatic java/lang/Integer/parseInt(Ljava/lang/String;)I
    putstatic _012_func_locals/sno_kw_STNO I
    return
Lkws_not_stno:
    aload_0
    ldc "STLIMIT"
    invokevirtual java/lang/String/equalsIgnoreCase(Ljava/lang/String;)Z
    ifeq Lkws_not_stlimit
    aload_1
    invokestatic java/lang/Integer/parseInt(Ljava/lang/String;)I
    putstatic _012_func_locals/sno_kw_STLIMIT I
    return
Lkws_not_stlimit:
    aload_0
    ldc "STCOUNT"
    invokevirtual java/lang/String/equalsIgnoreCase(Ljava/lang/String;)Z
    ifeq Lkws_not_stcount
    aload_1
    invokestatic java/lang/Integer/parseInt(Ljava/lang/String;)I
    putstatic _012_func_locals/sno_kw_STCOUNT I
    return
Lkws_not_stcount:
    return
.end method

.method static sno_var_put(Ljava/lang/String;Ljava/lang/String;)V
    .limit stack 4
    .limit locals 2
    aload_0
    ldc "OUTPUT"
    invokevirtual java/lang/String/equalsIgnoreCase(Ljava/lang/String;)Z
    ifeq Lsvp_not_output
    getstatic _012_func_locals/sno_stdout Ljava/io/PrintStream;
    aload_1
    invokevirtual java/io/PrintStream/println(Ljava/lang/String;)V
    return
Lsvp_not_output:
    getstatic _012_func_locals/sno_vars Ljava/util/HashMap;
    aload_0
    aload_1
    invokevirtual java/util/HashMap/put(Ljava/lang/Object;Ljava/lang/Object;)Ljava/lang/Object;
    pop
    aload_0
    aload_1
    invokestatic _012_func_locals/sno_mon_var(Ljava/lang/String;Ljava/lang/String;)V
    return
.end method

.method static sno_mon_var(Ljava/lang/String;Ljava/lang/String;)V
    .limit stack 6
    .limit locals 3
    getstatic _012_func_locals/sno_mon_fd Ljava/io/OutputStream;
    ifnull Lsmv_done
    new java/lang/StringBuilder
    dup
    invokespecial java/lang/StringBuilder/<init>()V
    ldc "VALUE"
    invokevirtual java/lang/StringBuilder/append(Ljava/lang/String;)Ljava/lang/StringBuilder;
    bipush 30
    invokevirtual java/lang/StringBuilder/append(C)Ljava/lang/StringBuilder;
    aload_0
    invokevirtual java/lang/StringBuilder/append(Ljava/lang/String;)Ljava/lang/StringBuilder;
    bipush 31
    invokevirtual java/lang/StringBuilder/append(C)Ljava/lang/StringBuilder;
    aload_1
    invokevirtual java/lang/StringBuilder/append(Ljava/lang/String;)Ljava/lang/StringBuilder;
    bipush 30
    invokevirtual java/lang/StringBuilder/append(C)Ljava/lang/StringBuilder;
    invokevirtual java/lang/StringBuilder/toString()Ljava/lang/String;
    ldc "UTF-8"
    invokevirtual java/lang/String/getBytes(Ljava/lang/String;)[B
    astore_2
    getstatic _012_func_locals/sno_mon_fd Ljava/io/OutputStream;
    aload_2
    invokevirtual java/io/OutputStream/write([B)V
    getstatic _012_func_locals/sno_mon_go_fd Ljava/io/InputStream;
    ifnull Lsmv_done
    getstatic _012_func_locals/sno_mon_go_fd Ljava/io/InputStream;
    invokevirtual java/io/InputStream/read()I
    istore_2
    iload_2
    bipush 71
    if_icmpeq Lsmv_done
    iconst_0
    invokestatic SnoRuntime/sno_exit(I)V
Lsmv_done:
    return
.end method

.method static sno_stcount_tick()V
    .limit stack 4
    .limit locals 0
    getstatic _012_func_locals/sno_kw_STCOUNT I
    iconst_1
    iadd
    putstatic _012_func_locals/sno_kw_STCOUNT I
    getstatic _012_func_locals/sno_kw_STLIMIT I
    iflt Lstick_ok
    getstatic _012_func_locals/sno_kw_STCOUNT I
    getstatic _012_func_locals/sno_kw_STLIMIT I
    if_icmple Lstick_ok
    getstatic java/lang/System/err Ljava/io/PrintStream;
    ldc "Termination: statement limit"
    invokevirtual java/io/PrintStream/println(Ljava/lang/String;)V
    iconst_1
    invokestatic SnoRuntime/sno_exit(I)V
Lstick_ok:
    return
.end method

.method static sno_indr_get(Ljava/lang/String;)Ljava/lang/String;
    .limit stack 4
    .limit locals 1
    getstatic _012_func_locals/sno_vars Ljava/util/HashMap;
    aload_0
    invokevirtual java/util/HashMap/get(Ljava/lang/Object;)Ljava/lang/Object;
    checkcast java/lang/String
    dup
    ifnonnull Lsig_done_indr
    pop
    ldc ""
Lsig_done_indr:
    areturn
.end method

.method static sno_indr_set(Ljava/lang/String;Ljava/lang/String;)V
    .limit stack 4
    .limit locals 2
    getstatic _012_func_locals/sno_vars Ljava/util/HashMap;
    aload_0
    aload_1
    invokevirtual java/util/HashMap/put(Ljava/lang/Object;Ljava/lang/Object;)Ljava/lang/Object;
    pop
    return
.end method

